{"request": {"departing": true, "url": "https://api.flightstats.com/flex/schedules/rest/v1/json/from/AJL/to/TRZ/departing/2021/05/10", "departureAirport": {"requestedCode": "AJL", "fsCode": "AJL"}, "arrivalAirport": {"requestedCode": "TRZ", "fsCode": "TRZ"}, "date": {"year": "2021", "month": "05", "day": "10", "interpreted": "2021-05-10"}}, "scheduledFlights": [], "appendix": {"airlines": [], "airports": [{"fs": "AJL", "iata": "AJL", "icao": "VEAZ", "faa": "", "name": "Aizawl Airport", "city": "Aizawl", "cityCode": "AJL", "countryCode": "IN", "countryName": "India", "regionName": "Asia", "timeZoneRegionName": "Asia/Kolkata", "weatherZone": "", "localTime": "2021-04-09T17:02:33.658", "utcOffsetHours": 5.5, "latitude": 23.838986, "longitude": 92.624815, "elevationFeet": 1000, "classification": 4, "active": true}, {"fs": "TRZ", "iata": "TRZ", "icao": "VOTR", "faa": "", "name": "Tiruchirapalli International Airport", "city": "Tiruchirappalli", "cityCode": "TRZ", "countryCode": "IN", "countryName": "India", "regionName": "Asia", "timeZoneRegionName": "Asia/Kolkata", "weatherZone": "", "localTime": "2021-04-09T17:02:33.658", "utcOffsetHours": 5.5, "latitude": 10.762168, "longitude": 78.707241, "elevationFeet": 279, "classification": 4, "active": true}], "equipments": []}}