{"request": {"departing": true, "url": "https://api.flightstats.com/flex/schedules/rest/v1/json/from/BLR/to/IXG/departing/2021/05/10", "departureAirport": {"requestedCode": "BLR", "fsCode": "BLR"}, "arrivalAirport": {"requestedCode": "IXG", "fsCode": "IXG"}, "date": {"year": "2021", "month": "05", "day": "10", "interpreted": "2021-05-10"}}, "scheduledFlights": [{"carrierFsCode": "6E", "flightNumber": "7181", "departureAirportFsCode": "BLR", "arrivalAirportFsCode": "IXG", "departureTime": "2021-05-10T13:40:00.000", "arrivalTime": "2021-05-10T15:00:00.000", "stops": 0, "flightEquipmentIataCode": "ATR", "isCodeshare": false, "isWetlease": false, "serviceType": "J", "serviceClasses": ["Y"], "trafficRestrictions": [], "codeshares": [], "referenceCode": "1558-880561--"}, {"carrierFsCode": "O2G", "flightNumber": "105", "departureAirportFsCode": "BLR", "arrivalAirportFsCode": "IXG", "departureTime": "2021-05-10T10:00:00.000", "arrivalTime": "2021-05-10T11:15:00.000", "stops": 0, "flightEquipmentIataCode": "ERJ", "isCodeshare": false, "isWetlease": false, "serviceType": "J", "serviceClasses": ["Y"], "trafficRestrictions": [], "codeshares": [], "referenceCode": "1558-47556--"}], "appendix": {"airlines": [{"fs": "O2G", "iata": "OG", "icao": "SDG", "name": "Ghodawat Enterprises", "active": true}, {"fs": "6E", "iata": "6E", "icao": "IGO", "name": "IndiGo", "active": true}], "airports": [{"fs": "BLR", "iata": "BLR", "icao": "VOBL", "faa": "", "name": "Kempegowda International Airport", "street1": "Kial Road, Devanahalli, Bengaluru, Karnataka 56030", "city": "Bengaluru", "cityCode": "BLR", "countryCode": "IN", "countryName": "India", "regionName": "Asia", "timeZoneRegionName": "Asia/Kolkata", "weatherZone": "", "localTime": "2021-04-09T17:50:03.297", "utcOffsetHours": 5.5, "latitude": 13.200771, "longitude": 77.710228, "elevationFeet": 2970, "classification": 2, "active": true}, {"fs": "IXG", "iata": "IXG", "icao": "VOBM", "faa": "", "name": "Belgaum Airport", "city": "Belgaum", "cityCode": "IXG", "countryCode": "IN", "countryName": "India", "regionName": "Asia", "timeZoneRegionName": "Asia/Kolkata", "weatherZone": "", "localTime": "2021-04-09T17:50:03.297", "utcOffsetHours": 5.5, "latitude": 15.858611, "longitude": 74.618333, "elevationFeet": 2488, "classification": 4, "active": true}], "equipments": [{"iata": "ERJ", "name": "Embraer RJ135 / RJ140 / RJ145", "turboProp": false, "jet": true, "widebody": false, "regional": true}, {"iata": "ATR", "name": "ATR 42 / ATR 72", "turboProp": true, "jet": false, "widebody": false, "regional": true}]}}