{"request": {"departing": true, "url": "https://api.flightstats.com/flex/schedules/rest/v1/json/from/GOP/to/RPR/departing/2021/05/10", "departureAirport": {"requestedCode": "GOP", "fsCode": "GOP"}, "arrivalAirport": {"requestedCode": "RPR", "fsCode": "RPR"}, "date": {"year": "2021", "month": "05", "day": "10", "interpreted": "2021-05-10"}}, "scheduledFlights": [], "appendix": {"airlines": [], "airports": [{"fs": "RPR", "iata": "RPR", "icao": "VARP", "faa": "", "name": "Swami Vivekananda Airport", "city": "Raipur", "cityCode": "RPR", "countryCode": "IN", "countryName": "India", "regionName": "Asia", "timeZoneRegionName": "Asia/Kolkata", "weatherZone": "", "localTime": "2021-04-09T18:23:01.326", "utcOffsetHours": 5.5, "latitude": 21.184561, "longitude": 81.739751, "elevationFeet": 1027, "classification": 4, "active": true}, {"fs": "GOP", "iata": "GOP", "icao": "VEGK", "faa": "", "name": "Gorakhpur Airport", "city": "Gorakhpur", "cityCode": "GOP", "countryCode": "IN", "countryName": "India", "regionName": "Asia", "timeZoneRegionName": "Asia/Kolkata", "weatherZone": "", "localTime": "2021-04-09T18:23:01.326", "utcOffsetHours": 5.5, "latitude": 26.746862, "longitude": 83.443762, "elevationFeet": 255, "classification": 4, "active": true}], "equipments": []}}