{"request": {"departing": true, "url": "https://api.flightstats.com/flex/schedules/rest/v1/json/from/PNQ/to/BLR/departing/2021/05/10", "departureAirport": {"requestedCode": "PNQ", "fsCode": "PNQ"}, "arrivalAirport": {"requestedCode": "BLR", "fsCode": "BLR"}, "date": {"year": "2021", "month": "05", "day": "10", "interpreted": "2021-05-10"}}, "scheduledFlights": [{"carrierFsCode": "6E", "flightNumber": "407", "departureAirportFsCode": "PNQ", "arrivalAirportFsCode": "BLR", "departureTime": "2021-05-10T14:05:00.000", "arrivalTime": "2021-05-10T15:35:00.000", "stops": 0, "flightEquipmentIataCode": "320", "isCodeshare": false, "isWetlease": false, "serviceType": "J", "serviceClasses": ["Y"], "trafficRestrictions": [], "codeshares": [], "referenceCode": "1558-889219--"}, {"carrierFsCode": "SG", "flightNumber": "517", "departureAirportFsCode": "PNQ", "arrivalAirportFsCode": "BLR", "departureTime": "2021-05-10T15:55:00.000", "arrivalTime": "2021-05-10T17:05:00.000", "stops": 0, "flightEquipmentIataCode": "737", "isCodeshare": false, "isWetlease": false, "serviceType": "J", "serviceClasses": ["R", "F", "J", "Y"], "trafficRestrictions": [], "codeshares": [], "referenceCode": "1558-258400--"}, {"carrierFsCode": "6E", "flightNumber": "103", "departureAirportFsCode": "PNQ", "arrivalAirportFsCode": "BLR", "departureTime": "2021-05-10T19:50:00.000", "arrivalTime": "2021-05-10T21:30:00.000", "stops": 0, "flightEquipmentIataCode": "320", "isCodeshare": false, "isWetlease": false, "serviceType": "J", "serviceClasses": ["Y"], "trafficRestrictions": [], "codeshares": [], "referenceCode": "1558-889243--"}, {"carrierFsCode": "G8", "flightNumber": "816", "departureAirportFsCode": "PNQ", "arrivalAirportFsCode": "BLR", "departureTime": "2021-05-10T19:10:00.000", "arrivalTime": "2021-05-10T20:30:00.000", "stops": 0, "flightEquipmentIataCode": "32A", "isCodeshare": false, "isWetlease": false, "serviceType": "J", "serviceClasses": ["Y"], "trafficRestrictions": [], "codeshares": [], "referenceCode": "1558-2009093--"}, {"carrierFsCode": "6E", "flightNumber": "6721", "departureAirportFsCode": "PNQ", "arrivalAirportFsCode": "BLR", "departureTime": "2021-05-10T08:10:00.000", "arrivalTime": "2021-05-10T09:35:00.000", "stops": 0, "flightEquipmentIataCode": "320", "isCodeshare": false, "isWetlease": false, "serviceType": "J", "serviceClasses": ["Y"], "trafficRestrictions": [], "codeshares": [], "referenceCode": "1558-889197--"}, {"carrierFsCode": "6E", "flightNumber": "483", "departureAirportFsCode": "PNQ", "arrivalAirportFsCode": "BLR", "departureTime": "2021-05-10T17:35:00.000", "arrivalTime": "2021-05-10T19:30:00.000", "stops": 0, "flightEquipmentIataCode": "320", "isCodeshare": false, "isWetlease": false, "serviceType": "J", "serviceClasses": ["Y"], "trafficRestrictions": [], "codeshares": [], "referenceCode": "1558-889236--"}, {"carrierFsCode": "I5*", "flightNumber": "1427", "departureAirportFsCode": "PNQ", "arrivalAirportFsCode": "BLR", "departureTime": "2021-05-10T19:25:00.000", "arrivalTime": "2021-05-10T20:45:00.000", "stops": 0, "flightEquipmentIataCode": "320", "isCodeshare": false, "isWetlease": false, "serviceType": "J", "serviceClasses": ["F", "J", "Y"], "trafficRestrictions": [], "codeshares": [], "referenceCode": "1558-2057571--"}, {"carrierFsCode": "I5*", "flightNumber": "1473", "departureAirportFsCode": "PNQ", "arrivalAirportFsCode": "BLR", "departureTime": "2021-05-10T13:00:00.000", "arrivalTime": "2021-05-10T14:20:00.000", "stops": 0, "flightEquipmentIataCode": "320", "isCodeshare": false, "isWetlease": false, "serviceType": "J", "serviceClasses": ["F", "J", "Y"], "trafficRestrictions": [], "codeshares": [], "referenceCode": "1558-2057555--"}, {"carrierFsCode": "G8", "flightNumber": "242", "departureAirportFsCode": "PNQ", "arrivalAirportFsCode": "BLR", "departureTime": "2021-05-10T17:30:00.000", "arrivalTime": "2021-05-10T18:50:00.000", "stops": 0, "flightEquipmentIataCode": "32A", "isCodeshare": false, "isWetlease": false, "serviceType": "J", "serviceClasses": ["Y"], "trafficRestrictions": [], "codeshares": [], "referenceCode": "1558-2009091--"}], "appendix": {"airlines": [{"fs": "G8", "iata": "G8", "icao": "GOW", "name": "GoAir", "active": true}, {"fs": "SG", "iata": "SG", "icao": "SEJ", "name": "SpiceJet", "active": true}, {"fs": "6E", "iata": "6E", "icao": "IGO", "name": "IndiGo", "active": true}, {"fs": "I5*", "iata": "I5", "icao": "IAD", "name": "AirAsia India", "active": true}], "airports": [{"fs": "PNQ", "iata": "PNQ", "icao": "VAPO", "faa": "", "name": "Pune Airport", "city": "Pune", "cityCode": "PNQ", "countryCode": "IN", "countryName": "India", "regionName": "Asia", "timeZoneRegionName": "Asia/Kolkata", "weatherZone": "", "localTime": "2021-04-09T18:03:24.325", "utcOffsetHours": 5.5, "latitude": 18.581389, "longitude": 73.920556, "elevationFeet": 1942, "classification": 3, "active": true}, {"fs": "BLR", "iata": "BLR", "icao": "VOBL", "faa": "", "name": "Kempegowda International Airport", "street1": "Kial Road, Devanahalli, Bengaluru, Karnataka 56030", "city": "Bengaluru", "cityCode": "BLR", "countryCode": "IN", "countryName": "India", "regionName": "Asia", "timeZoneRegionName": "Asia/Kolkata", "weatherZone": "", "localTime": "2021-04-09T18:03:24.325", "utcOffsetHours": 5.5, "latitude": 13.200771, "longitude": 77.710228, "elevationFeet": 2970, "classification": 2, "active": true}], "equipments": [{"iata": "320", "name": "Airbus A320", "turboProp": false, "jet": true, "widebody": false, "regional": false}, {"iata": "32A", "name": "Airbus A320 (sharklets)", "turboProp": false, "jet": true, "widebody": false, "regional": false}, {"iata": "737", "name": "Boeing 737 Passenger", "turboProp": false, "jet": true, "widebody": false, "regional": false}]}}